toolbox_az/__init__.py
toolbox_az-0.3.dist-info/METADATA
toolbox_az-0.3.dist-info/WHEEL
toolbox_az-0.3.dist-info/top_level.txt
toolbox_az-0.3.dist-info/RECORD
