Metadata-Version: 2.1
Name: toolbox-az
Version: 0.3
Summary: Toolbox with some useful utils to be used in projects.
Home-page: https://github.com/advaza/toolbox
Author: Adva Zair
Author-email: adva@lightricks.com
License: MIT
Platform: UNKNOWN
Requires-Dist: tensorflow
Requires-Dist: numpy
